{
    "version": "0.2",
    "language": "en",
    "ignorePaths": [],
    "dictionaryDefinitions": [],
    "dictionaries": [
        "fullstack",
        "softwareTerms",
        "csharp",
        "typescript",
        "html",
        "css"
    ],
    "words": [
        "cloudflared",
        "cooldown",
        "Demiplane",
        "discordsays",
        "freedraw",
        "hoverable",
        "Newtonsoft",
        "ondelete",
        "onlayerchange",
        "onmovedown",
        "onmoveup",
        "ontransform",
        "resizebox",
        "serverstatus",
        "setlayer",
        "tokendraw",
        "tokenedit",
        "tokenlist",
        "tokenmap",
        "usercursors",
        "vitest",
        "wwwroot",
        "xmark"
    ],
    "ignoreWords": [],
    "import": []
}
